{
    "following_count": 59, 
    "user_type": "people", 
    "account_status": [], 
    "id": "9a245e0a433b4a6d0de052fbb13d2870", 
    "voteup_count": 45936, 
    "headline": "\u9752\u9510\u521b\u6295\u5408\u4f19\u4eba/\u54f2\u5b66/\u81ea\u7136/\u793e\u79d1", 
    "is_advertiser": false, 
    "is_org": false, 
    "follower_count": 18607, 
    "employments": [
        {
            "company": {
                "name": "\u9752\u9510\u521b\u6295", 
                "url": "", 
                "excerpt": "", 
                "introduction": "", 
                "avatar_url": "https://pic1.zhimg.com/e82bab09c_is.jpg", 
                "type": "topic", 
                "id": ""
            }, 
            "job": {
                "name": "\u521b\u59cb\u5408\u4f19\u4eba", 
                "url": "", 
                "excerpt": "", 
                "introduction": "", 
                "avatar_url": "https://pic1.zhimg.com/e82bab09c_is.jpg", 
                "type": "topic", 
                "id": "19728250"
            }
        }
    ], 
    "type": "people", 
    "avatar_url_template": "https://pic3.zhimg.com/v2-7184b9dc09e6751f5b61add18e52fc7e_{size}.jpg", 
    "description": "\u505a\u597d\u6295\u8d44\uff0c\u611f\u609f\u751f\u6d3b\uff0c\u53ea\u8bf4\u771f\u8bdd <a href=\"https://link.zhihu.com/?target=http%3A//www.edgevc.com.cn\" class=\" external\" target=\"_blank\" rel=\"nofollow noreferrer\"><span class=\"invisible\">http://www.</span><span class=\"visible\">edgevc.com.cn</span><span class=\"invisible\"></span><i class=\"icon-external\"></i></a><br><br>\u79c1\u4fe1\u7531\u540c\u4e8b\u7ef4\u62a4\uff0c\u5982\u9700\u8054\u7cfb\u672c\u4eba\u8bf7\u4e0a\u201c\u5728\u884c\u201d\u8054\u7cfb\u6211\u5df2\u59d4\u6258\u201c\u7ef4\u6743\u9a91\u58eb\u201d\uff08<a href=\"https://link.zhihu.com/?target=http%3A//rightknights.com\" class=\" external\" target=\"_blank\" rel=\"nofollow noreferrer\"><span class=\"invisible\">http://</span><span class=\"visible\">rightknights.com</span><span class=\"invisible\"></span><i class=\"icon-external\"></i></a>\uff09\u4e3a\u6211\u7684\u6587\u7ae0\u8fdb\u884c\u7ef4\u6743", 
    "locations": [
        {
            "name": "\u4e0a\u6d77", 
            "url": "", 
            "excerpt": "\u4e0a\u6d77\uff0c\u53c8\u79f0\u300c\u4e0a\u6d77\u6ee9\u300d\u3002\u4e2d\u56fd\u7b2c\u4e00\u5927\u57ce\u5e02\uff0c\u56db\u5927\u76f4\u8f96\u5e02\u4e4b\u4e00\uff0c\u4e2d\u56fd\u56fd\u5bb6\u4e2d\u5fc3\u57ce\u5e02\uff0c\u4e2d\u56fd\u7684\u7ecf\u6d4e\u3001\u79d1\u6280\u3001\u5de5\u4e1a\u3001\u91d1\u878d\u3001\u8d38\u6613\u3001\u4f1a\u5c55\u548c\u822a\u8fd0\u4e2d\u5fc3\u3002\u4e0a\u6d77\u4f4d\u4e8e\u4e2d\u56fd\u5927\u9646\u6d77\u5cb8\u7ebf\u4e2d\u90e8\u957f\u6c5f\u53e3\uff0c\u62e5\u6709\u4e2d\u56fd\u6700\u5927\u5916\u8d38\u6e2f\u53e3\u548c\u6700\u5927\u5de5\u4e1a\u57fa\u5730\u3002\u9694\u6d77\u4e0e\u65e5\u672c\u4e5d\u5dde\u5c9b\u76f8\u671b\uff0c\u5357\u6fd2\u676d\u5dde\u6e7e\uff0c\u897f\u90e8\u4e0e\u6c5f\u82cf\u3001\u6d59\u6c5f\u4e24\u7701\u76f8\u63a5\u3002\u4e0a\u6d77\u6e2f\u8d27\u7269\u541e\u5410\u91cf\u5c45\u4e16\u754c\u7b2c\u4e00\u3002\u4e0a\u6d77\u662f\u4e00\u5ea7\u65b0\u5174\u7684\u65c5\u6e38\u57ce\u5e02\uff0c\u6709\u6df1\u539a\u8fd1\u4ee3\u57ce\u5e02\u6587\u5316\u5e95\u8574\u548c\u4f17\u591a\u5386\u53f2\u53e4\u8ff9\uff0c\u4e3e\u529e\u8fc7\u4e16\u535a\u4f1a\u3002\u6c5f\u5357\u7684\u4f20\u7edf\u4e0e\u79fb\u6c11\u5e26\u5165\u7684\u6587\u5316\u878d\u5408\uff0c\u9010\u6e10\u5f62\u2026", 
            "introduction": "\u4e0a\u6d77\uff0c\u53c8\u79f0\u300c\u4e0a\u6d77\u6ee9\u300d\u3002\u4e2d\u56fd\u7b2c\u4e00\u5927\u57ce\u5e02\uff0c\u56db\u5927\u76f4\u8f96\u5e02\u4e4b\u4e00\uff0c\u4e2d\u56fd\u56fd\u5bb6\u4e2d\u5fc3\u57ce\u5e02\uff0c\u4e2d\u56fd\u7684\u7ecf\u6d4e\u3001\u79d1\u6280\u3001\u5de5\u4e1a\u3001\u91d1\u878d\u3001\u8d38\u6613\u3001\u4f1a\u5c55\u548c\u822a\u8fd0\u4e2d\u5fc3\u3002\u4e0a\u6d77\u4f4d\u4e8e\u4e2d\u56fd\u5927\u9646\u6d77\u5cb8\u7ebf\u4e2d\u90e8\u957f\u6c5f\u53e3\uff0c\u62e5\u6709\u4e2d\u56fd\u6700\u5927\u5916\u8d38\u6e2f\u53e3\u548c\u6700\u5927\u5de5\u4e1a\u57fa\u5730\u3002\u9694\u6d77\u4e0e\u65e5\u672c\u4e5d\u5dde\u5c9b\u76f8\u671b\uff0c\u5357\u6fd2\u676d\u5dde\u6e7e\uff0c\u897f\u90e8\u4e0e\u6c5f\u82cf\u3001\u6d59\u6c5f\u4e24\u7701\u76f8\u63a5\u3002\u4e0a\u6d77\u6e2f\u8d27\u7269\u541e\u5410\u91cf\u5c45\u4e16\u754c\u7b2c\u4e00\u3002\u4e0a\u6d77\u662f\u4e00\u5ea7\u65b0\u5174\u7684\u65c5\u6e38\u57ce\u5e02\uff0c\u6709\u6df1\u539a\u8fd1\u4ee3\u57ce\u5e02\u6587\u5316\u5e95\u8574\u548c\u4f17\u591a\u5386\u53f2\u53e4\u8ff9\uff0c\u4e3e\u529e\u8fc7\u4e16\u535a\u4f1a\u3002\u6c5f\u5357\u7684\u4f20\u7edf\u4e0e\u79fb\u6c11\u5e26\u5165\u7684\u6587\u5316\u878d\u5408\uff0c\u9010\u6e10\u5f62\u6210\u4e86\u7279\u6709\u7684\u6d77\u6d3e\u6587\u5316\u3002\u4e0a\u6d77\u65e9\u5df2\u6210\u4e3a\u56fd\u9645\u5927\u90fd\u5e02\uff0c\u5e76\u81f4\u529b\u4e8e\u57282020\u5e74\u5efa\u8bbe\u6210\u4e3a\u56fd\u9645\u91d1\u878d\u548c\u822a\u8fd0\u4e2d\u5fc3\u3002", 
            "avatar_url": "https://pic2.zhimg.com/aea66d640b12450a861282066d78bb2d_is.jpg", 
            "type": "topic", 
            "id": "19550818"
        }
    ], 
    "educations": [
        {
            "major": {
                "name": "\u5fae\u7535\u5b50", 
                "url": "", 
                "excerpt": "", 
                "introduction": "", 
                "avatar_url": "https://pic2.zhimg.com/766551bd1_is.jpg", 
                "type": "topic", 
                "id": "19579527"
            }, 
            "school": {
                "name": "\u4e0a\u6d77\u4ea4\u901a\u5927\u5b66", 
                "url": "", 
                "excerpt": "\u4e0a\u6d77\u4ea4\u901a\u5927\u5b66\u662f\u6211\u56fd\u5386\u53f2\u6700\u60a0\u4e45\u3001\u4eab\u8a89\u6d77\u5185\u5916\u7684\u9ad8\u7b49\u5b66\u5e9c\u4e4b\u4e00\uff0c\u662f\u6559\u80b2\u90e8\u76f4\u5c5e\u5e76\u4e0e\u4e0a\u6d77\u5e02\u5171\u5efa\u7684\u5168\u56fd\u91cd\u70b9\u5927\u5b66\u3002\u7ecf\u8fc7120\u5e74\u7684\u4e0d\u61c8\u52aa\u529b\uff0c\u4e0a\u6d77\u4ea4\u901a\u5927\u5b66\u5df2\u7ecf\u6210\u4e3a\u4e00\u6240\u201c\u7efc\u5408\u6027\u3001\u7814\u7a76\u578b\u3001\u56fd\u9645\u5316\u201d\u7684\u56fd\u5185\u4e00\u6d41\u3001\u56fd\u9645\u77e5\u540d\u5927\u5b66\u3002\u5728\u6d77\u5ce1\u4e24\u5cb8\uff0c\u4e0a\u6d77\u4ea4\u901a\u5927\u5b66\u4e0e\u5317\u4eac\u4ea4\u901a\u5927\u5b66\uff0c\u897f\u5357\u4ea4\u901a\u5927\u5b66\uff0c\u56fd\u7acb\u4ea4\u901a\u5927\u5b66\uff0c\u897f\u5b89\u4ea4\u901a\u5927\u5b66\uff0c\u5171\u79f0\u300c\u4e94\u6821\u4e00\u5bb6\u300d\u3002 \u6765\u6e90\uff1a\u4ea4\u5927\u6982\u51b5-\u4e0a\u6d77\u4ea4\u901a\u5927\u5b66 ", 
                "introduction": "\u4e0a\u6d77\u4ea4\u901a\u5927\u5b66\u662f\u6211\u56fd\u5386\u53f2\u6700\u60a0\u4e45\u3001\u4eab\u8a89\u6d77\u5185\u5916\u7684\u9ad8\u7b49\u5b66\u5e9c\u4e4b\u4e00\uff0c\u662f\u6559\u80b2\u90e8\u76f4\u5c5e\u5e76\u4e0e\u4e0a\u6d77\u5e02\u5171\u5efa\u7684\u5168\u56fd\u91cd\u70b9\u5927\u5b66\u3002\u7ecf\u8fc7120\u5e74\u7684\u4e0d\u61c8\u52aa\u529b\uff0c\u4e0a\u6d77\u4ea4\u901a\u5927\u5b66\u5df2\u7ecf\u6210\u4e3a\u4e00\u6240\u201c\u7efc\u5408\u6027\u3001\u7814\u7a76\u578b\u3001\u56fd\u9645\u5316\u201d\u7684\u56fd\u5185\u4e00\u6d41\u3001\u56fd\u9645\u77e5\u540d\u5927\u5b66\u3002\u5728\u6d77\u5ce1\u4e24\u5cb8\uff0c\u4e0a\u6d77\u4ea4\u901a\u5927\u5b66\u4e0e\u5317\u4eac\u4ea4\u901a\u5927\u5b66\uff0c\u897f\u5357\u4ea4\u901a\u5927\u5b66\uff0c\u56fd\u7acb\u4ea4\u901a\u5927\u5b66\uff0c\u897f\u5b89\u4ea4\u901a\u5927\u5b66\uff0c\u5171\u79f0\u300c\u4e94\u6821\u4e00\u5bb6\u300d\u3002<br><br>\u6765\u6e90\uff1a<a href=\"http://www.sjtu.edu.cn/zdh/jdgk.htm\" data-editable=\"true\" data-title=\"\u4ea4\u5927\u6982\u51b5-\u4e0a\u6d77\u4ea4\u901a\u5927\u5b66\" class=\"\">\u4ea4\u5927\u6982\u51b5-\u4e0a\u6d77\u4ea4\u901a\u5927\u5b66</a>", 
                "avatar_url": "https://pic2.zhimg.com/286e5502e28fb14adab3a047a46a64d9_is.jpg", 
                "type": "topic", 
                "id": "19575211"
            }
        }
    ], 
    "url_token": "wu-bin-817", 
    "name": "\u9752\u9510\u5434\u658c", 
    "url": "http://www-nweb-api-member/people/9a245e0a433b4a6d0de052fbb13d2870", 
    "badge": [
        {
            "type": "identity", 
            "description": "\u4e0a\u6d77\u4ea4\u901a\u5927\u5b66 \u5fae\u7535\u5b50\u4e0e\u56fa\u4f53\u7535\u5b50\u5b66\u535a\u58eb"
        }
    ], 
    "avatar_url": "https://pic3.zhimg.com/v2-7184b9dc09e6751f5b61add18e52fc7e_is.jpg", 
    "thanked_count": 10019, 
    "gender": 1
}